adafruit_vcnl4010.py
adafruit_circuitpython_vcnl4010-0.11.16.dist-info/licenses/LICENSE
adafruit_circuitpython_vcnl4010-0.11.16.dist-info/METADATA
adafruit_circuitpython_vcnl4010-0.11.16.dist-info/WHEEL
adafruit_circuitpython_vcnl4010-0.11.16.dist-info/top_level.txt
adafruit_circuitpython_vcnl4010-0.11.16.dist-info/RECORD
